pdfforms/__init__.py
pdfforms/cli.py
pdfforms/fdf.py
pdfforms/field_def.py
pdfforms/fill.py
pdfforms/inspect.py
pdfforms/pdfforms.py
pdfforms/pdftk.py
pdfforms/spreadsheet.py
pdfforms/transforms.py
pdfforms/version.py
pdfforms-2.0.0.dist-info/AUTHORS.rst
pdfforms-2.0.0.dist-info/LICENSE.txt
pdfforms-2.0.0.dist-info/METADATA
pdfforms-2.0.0.dist-info/WHEEL
pdfforms-2.0.0.dist-info/entry_points.txt
pdfforms-2.0.0.dist-info/top_level.txt
pdfforms-2.0.0.dist-info/RECORD
