Metadata-Version: 2.1
Name: pdfforms
Version: 2.0.0
Summary: Populate fillable pdf forms from csv data file
Home-page: https://github.com/altaurog/pdfforms
Author: Aryeh Leib Taurog
Author-email: python@aryehleib.com
License: MIT
Platform: UNKNOWN
Classifier: Programming Language :: Python :: 3.5
Classifier: Programming Language :: Python :: 3.6
Classifier: Programming Language :: Python :: 3.7
Classifier: Programming Language :: Python :: 3.8
Classifier: Programming Language :: Python :: 3.9
Classifier: Development Status :: 5 - Production/Stable
Classifier: License :: OSI Approved :: MIT License
Classifier: Operating System :: OS Independent
Classifier: Intended Audience :: End Users/Desktop
Classifier: Environment :: Console
Classifier: Topic :: Office/Business
Requires-Dist: pyexcel
Provides-Extra: csv
Requires-Dist: pyexcel-io ; extra == 'csv'
Provides-Extra: ods
Requires-Dist: pyexcel-ods ; extra == 'ods'
Provides-Extra: xlsx
Requires-Dist: pyexcel-xlsx ; extra == 'xlsx'
